[
    {
        "layout_dets": [
            {
                "category_id": 1,
                "poly": [
                    194,
                    388,
                    1461,
                    388,
                    1461,
                    560,
                    194,
                    560
                ],
                "score": 0.968
            },
            {
                "category_id": 1,
                "poly": [
                    193,
                    1168,
                    1463,
                    1168,
                    1463,
                    1403,
                    193,
                    1403
                ],
                "score": 0.967
            },
            {
                "category_id": 1,
                "poly": [
                    195,
                    1428,
                    1461,
                    1428,
                    1461,
                    1533,
                    195,
                    1533
                ],
                "score": 0.95
            },
            {
                "category_id": 1,
                "poly": [
                    195,
                    1622,
                    1461,
                    1622,
                    1461,
                    1726,
                    195,
                    1726
                ],
                "score": 0.949
            },
            {
                "category_id": 1,
                "poly": [
                    196,
                    974,
                    1462,
                    974,
                    1462,
                    1079,
                    196,
                    1079
                ],
                "score": 0.948
            },
            {
                "category_id": 0,
                "poly": [
                    578,
                    205,
                    1075,
                    205,
                    1075,
                    278,
                    578,
                    278
                ],
                "score": 0.947
            },
            {
                "category_id": 1,
                "poly": [
                    195,
                    714,
                    1463,
                    714,
                    1463,
                    819,
                    195,
                    819
                ],
                "score": 0.944
            },
            {
                "category_id": 1,
                "poly": [
                    195,
                    844,
                    1462,
                    844,
                    1462,
                    948,
                    195,
                    948
                ],
                "score": 0.94
            },
            {
                "category_id": 0,
                "poly": [
                    262,
                    649,
                    600,
                    649,
                    600,
                    691,
                    262,
                    691
                ],
                "score": 0.891
            },
            {
                "category_id": 0,
                "poly": [
                    261,
                    1103,
                    636,
                    1103,
                    636,
                    1144,
                    261,
                    1144
                ],
                "score": 0.874
            },
            {
                "category_id": 1,
                "poly": [
                    255,
                    583,
                    1381,
                    583,
                    1381,
                    625,
                    255,
                    625
                ],
                "score": 0.872
            },
            {
                "category_id": 0,
                "poly": [
                    273,
                    1558,
                    746,
                    1558,
                    746,
                    1598,
                    273,
                    1598
                ],
                "score": 0.701
            },
            {
                "category_id": 1,
                "poly": [
                    273,
                    1558,
                    746,
                    1558,
                    746,
                    1598,
                    273,
                    1598
                ],
                "score": 0.215
            },
            {
                "category_id": 15,
                "poly": [
                    575.0,
                    204.0,
                    1079.0,
                    204.0,
                    1079.0,
                    286.0,
                    575.0,
                    286.0
                ],
                "score": 1.0,
                "text": ""
            },
            {
                "category_id": 15,
                "poly": [
                    262.0,
                    649.0,
                    599.0,
                    649.0,
                    599.0,
                    689.0,
                    262.0,
                    689.0
                ],
                "score": 1.0,
                "text": ""
            },
            {
                "category_id": 15,
                "poly": [
                    263.0,
                    1104.0,
                    633.0,
                    1104.0,
                    633.0,
                    1146.0,
                    263.0,
                    1146.0
                ],
                "score": 1.0,
                "text": ""
            },
            {
                "category_id": 15,
                "poly": [
                    280.0,
                    1559.0,
                    747.0,
                    1559.0,
                    747.0,
                    1598.0,
                    280.0,
                    1598.0
                ],
                "score": 1.0,
                "text": ""
            },
            {
                "category_id": 15,
                "poly": [
                    264.0,
                    390.0,
                    1457.0,
                    390.0,
                    1457.0,
                    430.0,
                    264.0,
                    430.0
                ],
                "score": 1.0,
                "text": ""
            },
            {
                "category_id": 15,
                "poly": [
                    197.0,
                    456.0,
                    1440.0,
                    456.0,
                    1440.0,
                    495.0,
                    197.0,
                    495.0
                ],
                "score": 1.0,
                "text": ""
            },
            {
                "category_id": 15,
                "poly": [
                    197.0,
                    522.0,
                    947.0,
                    522.0,
                    947.0,
                    558.0,
                    197.0,
                    558.0
                ],
                "score": 1.0,
                "text": ""
            },
            {
                "category_id": 15,
                "poly": [
                    277.0,
                    1169.0,
                    1456.0,
                    1169.0,
                    1456.0,
                    1206.0,
                    277.0,
                    1206.0
                ],
                "score": 1.0,
                "text": ""
            },
            {
                "category_id": 15,
                "poly": [
                    197.0,
                    1235.0,
                    1457.0,
                    1235.0,
                    1457.0,
                    1272.0,
                    197.0,
                    1272.0
                ],
                "score": 1.0,
                "text": ""
            },
            {
                "category_id": 15,
                "poly": [
                    197.0,
                    1299.0,
                    1459.0,
                    1299.0,
                    1459.0,
                    1336.0,
                    197.0,
                    1336.0
                ],
                "score": 1.0,
                "text": ""
            },
            {
                "category_id": 15,
                "poly": [
                    197.0,
                    1363.0,
                    650.0,
                    1363.0,
                    650.0,
                    1401.0,
                    197.0,
                    1401.0
                ],
                "score": 1.0,
                "text": ""
            },
            {
                "category_id": 15,
                "poly": [
                    276.0,
                    1426.0,
                    1460.0,
                    1426.0,
                    1460.0,
                    1469.0,
                    276.0,
                    1469.0
                ],
                "score": 1.0,
                "text": ""
            },
            {
                "category_id": 15,
                "poly": [
                    196.0,
                    1493.0,
                    583.0,
                    1493.0,
                    583.0,
                    1533.0,
                    196.0,
                    1533.0
                ],
                "score": 1.0,
                "text": ""
            },
            {
                "category_id": 15,
                "poly": [
                    260.0,
                    1620.0,
                    1460.0,
                    1620.0,
                    1460.0,
                    1663.0,
                    260.0,
                    1663.0
                ],
                "score": 1.0,
                "text": ""
            },
            {
                "category_id": 15,
                "poly": [
                    189.0,
                    1680.0,
                    289.0,
                    1680.0,
                    289.0,
                    1735.0,
                    189.0,
                    1735.0
                ],
                "score": 1.0,
                "text": ""
            },
            {
                "category_id": 15,
                "poly": [
                    280.0,
                    974.0,
                    1458.0,
                    974.0,
                    1458.0,
                    1014.0,
                    280.0,
                    1014.0
                ],
                "score": 1.0,
                "text": ""
            },
            {
                "category_id": 15,
                "poly": [
                    196.0,
                    1038.0,
                    1314.0,
                    1038.0,
                    1314.0,
                    1078.0,
                    196.0,
                    1078.0
                ],
                "score": 1.0,
                "text": ""
            },
            {
                "category_id": 15,
                "poly": [
                    280.0,
                    717.0,
                    1457.0,
                    717.0,
                    1457.0,
                    752.0,
                    280.0,
                    752.0
                ],
                "score": 1.0,
                "text": ""
            },
            {
                "category_id": 15,
                "poly": [
                    196.0,
                    779.0,
                    1382.0,
                    779.0,
                    1382.0,
                    819.0,
                    196.0,
                    819.0
                ],
                "score": 1.0,
                "text": ""
            },
            {
                "category_id": 15,
                "poly": [
                    277.0,
                    843.0,
                    1458.0,
                    843.0,
                    1458.0,
                    883.0,
                    277.0,
                    883.0
                ],
                "score": 1.0,
                "text": ""
            },
            {
                "category_id": 15,
                "poly": [
                    188.0,
                    899.0,
                    256.0,
                    899.0,
                    256.0,
                    958.0,
                    188.0,
                    958.0
                ],
                "score": 1.0,
                "text": ""
            },
            {
                "category_id": 15,
                "poly": [
                    262.0,
                    582.0,
                    1380.0,
                    582.0,
                    1380.0,
                    626.0,
                    262.0,
                    626.0
                ],
                "score": 1.0,
                "text": ""
            },
            {
                "category_id": 15,
                "poly": [
                    280.0,
                    1559.0,
                    747.0,
                    1559.0,
                    747.0,
                    1598.0,
                    280.0,
                    1598.0
                ],
                "score": 1.0,
                "text": ""
            }
        ],
        "page_info": {
            "page_no": 0,
            "width": 1654,
            "height": 2339
        }
    }
]